main_module/__init__.py
main_module/main.py
apps_support-0.1.0.dist-info/LICENSE
apps_support-0.1.0.dist-info/METADATA
apps_support-0.1.0.dist-info/WHEEL
apps_support-0.1.0.dist-info/top_level.txt
apps_support-0.1.0.dist-info/RECORD
