Metadata-Version: 2.1
Name: apps_support
Version: 0.1.0
Summary: Простая библиотека для MaxOS
Author: fhghfhfhfh
Author-email: maxim.parkhomenko@internet.ru
Classifier: Programming Language :: Python :: 3
Classifier: License :: OSI Approved :: MIT License
Classifier: Operating System :: OS Independent
Requires-Python: >=3.12
License-File: LICENSE
